pymathtools.py
pymathtools-1.1.dist-info/LICENSE
pymathtools-1.1.dist-info/METADATA
pymathtools-1.1.dist-info/WHEEL
pymathtools-1.1.dist-info/top_level.txt
pymathtools-1.1.dist-info/RECORD
