Metadata-Version: 2.1
Name: pymathtools
Version: 1.1
Summary: A really simple Python library to do some math operations
Author: Sean-e
Author-email: Sean-e <seane410@gmail.com>
Project-URL: Homepage, https://github.com/JrGamer410/pymathtools
Project-URL: Issues, https://github.com/JrGamer410/pymathtools/issues
Classifier: Programming Language :: Python :: 3
Classifier: License :: OSI Approved :: MIT License
Classifier: Operating System :: OS Independent
License-File: LICENSE
